main_application.py
utils.py
controllers/cluster_status_controller.py
controllers/job_panel_controller.py
controllers/job_queue_controller.py
controllers/settings_controller.py
core/defaults.py
core/event_bus.py
core/slurm_api.py
core/slurm_worker.py
core/style.py
core/terminal_helper.py
models/cluster_status_model.py
models/job_queue_model.py
models/project_model.py
models/settings_model.py
slurm_aio_gui-1.0.9.dist-info/licenses/LICENSE
src_static/app_logo.png
src_static/assignment_32dp_00B32D_FILL0_wght400_GRAD0_opsz40.svg
src_static/bad_connection.png
src_static/cancel.svg
src_static/check.svg
src_static/checkmark.svg
src_static/clock.svg
src_static/cloud_off_24dp_EA3323_FILL0_wght400_GRAD0_opsz24.png
src_static/cluster_status.webp
src_static/dark_theme.txt
src_static/defaults.ini
src_static/delete.svg
src_static/down_arrow.svg
src_static/duplicate.svg
src_static/edit.svg
src_static/err.svg
src_static/file.svg
src_static/filter.png
src_static/folder.svg
src_static/good_connection.png
src_static/home.svg
src_static/info.svg
src_static/job_panel.webp
src_static/light_theme.txt
src_static/loading.gif
src_static/loading_2.gif
src_static/new_folder.svg
src_static/next_folder.svg
src_static/ok.svg
src_static/pending.svg
src_static/plus.png
src_static/prev_folder.svg
src_static/refresh.svg
src_static/settings_24dp_E3E3E3_FILL0_wght400_GRAD0_opsz24.svg
src_static/settings_32dp_00B32D_FILL0_wght400_GRAD0_opsz40.svg
src_static/star.svg
src_static/start.svg
src_static/stop.svg
src_static/submit.svg
src_static/terminal.svg
src_static/toggle_off_24dp_999999_FILL0_wght400_GRAD0_opsz24.svg
src_static/up_arrow.svg
src_static/up_folder.svg
src_static/view_logs.svg
src_static/warning.svg
views/cluster_entities.py
views/cluster_status_view.py
views/job_queue_view.py
views/jobs_panel_view.py
views/jobs_view.py
views/project_view.py
views/settings_view.py
widgets/cluster_status_widget.py
widgets/job_queue_widget.py
widgets/jobs_panel_widget.py
widgets/log_viewer_widget.py
widgets/new_job_widget.py
slurm_aio_gui-1.0.9.dist-info/METADATA
slurm_aio_gui-1.0.9.dist-info/WHEEL
slurm_aio_gui-1.0.9.dist-info/entry_points.txt
slurm_aio_gui-1.0.9.dist-info/top_level.txt
slurm_aio_gui-1.0.9.dist-info/RECORD
