Metadata-Version: 2.4
Name: slurm-aio-gui
Version: 1.0.9
Summary: A modern, cross-platform GUI for managing and monitoring SLURM clusters.
Author-email: Morelli-01 <nicolamorelli30008@gmail.com>
License: MIT License
Project-URL: Homepage, https://github.com/Morelli-01/slurm_gui
Project-URL: Bug Tracker, https://github.com/Morelli-01/slurm_gui/issues
Classifier: License :: OSI Approved :: MIT License
Classifier: Operating System :: OS Independent
Classifier: Programming Language :: Python :: 3
Classifier: Programming Language :: Python :: 3.8
Classifier: Programming Language :: Python :: 3.9
Classifier: Programming Language :: Python :: 3.10
Classifier: Programming Language :: Python :: 3.11
Classifier: Topic :: Scientific/Engineering
Classifier: Development Status :: 4 - Beta
Classifier: Environment :: X11 Applications :: Qt
Requires-Python: >=3.8
License-File: LICENSE
Requires-Dist: bcrypt==4.3.0
Requires-Dist: certifi==2025.4.26
Requires-Dist: cffi==1.17.1
Requires-Dist: charset-normalizer==3.4.2
Requires-Dist: cryptography==45.0.3
Requires-Dist: idna==3.10
Requires-Dist: paramiko==3.5.1
Requires-Dist: pycparser==2.22
Requires-Dist: PyNaCl==1.5.0
Requires-Dist: PyQt6==6.9.0
Requires-Dist: PyQt6-Qt6==6.9.0
Requires-Dist: PyQt6_sip==13.10.2
Requires-Dist: requests==2.32.3
Requires-Dist: urllib3==2.4.0
Requires-Dist: packaging
Requires-Dist: toml
Dynamic: license-file
